{
  "public": {
    "graphQL": {
      "httpUri": "http://localhost:3000/graphql"
    },
    "productName": "Product Name",
    "copyrightStartYear": "2018",
    "twitterUsername": "product",
    "facebookUsername": "product",
    "productAddress": "1658 N. Milwaukee Ave., #393, Chicago, IL 60647"
  },
  "private": {
    "MAIL_URL": "",
    "OAuth": {
      "facebook": {
        "enabled": true,
        "appId": "",
        "secret": "",
        "loginStyle": "popup"
      },
      "google": {
        "enabled": true,
        "clientId": "",
        "secret": "",
        "loginStyle": "popup"
      },
      "github": {
        "enabled": true,
        "clientId": "",
        "secret": "",
        "loginStyle": "popup"
      }
    },
    "supportEmail": "Customer Support <support@product.com>"
  }
}
